{
  "b": 209,
  "disableInputWhenNotFocused": true,
  "mangledName": "Main_32Menu",
  "name": "Main Menu",
  "oglFOV": 90,
  "oglZFar": 500,
  "oglZNear": 1,
  "r": 209,
  "standardSortMethod": true,
  "stopSoundsOnStartup": true,
  "title": "",
  "v": 209,
  "uiSettings": {
    "grid": false,
    "gridType": "rectangular",
    "gridWidth": 32,
    "gridHeight": 32,
    "gridOffsetX": 0,
    "gridOffsetY": 0,
    "gridColor": 10401023,
    "gridAlpha": 0.8,
    "snap": false,
    "zoomFactor": 0.6965000000000007,
    "windowMask": false
  },
  "objectsGroups": [],
  "variables": [],
  "instances": [
    {
      "angle": 0,
      "customSize": false,
      "height": 0,
      "layer": "",
      "locked": false,
      "name": "Link",
      "persistentUuid": "c3c59d52-cd0c-4ec4-a0e9-21961ada0fe6",
      "width": 0,
      "x": 48,
      "y": 28,
      "zOrder": 1,
      "numberProperties": [],
      "stringProperties": [],
      "initialVariables": [
        {
          "name": "to",
          "type": "string",
          "value": "prototype"
        },
        {
          "name": "name",
          "type": "string",
          "value": "Test platformer with events"
        }
      ]
    },
    {
      "angle": 0,
      "customSize": false,
      "height": 0,
      "layer": "",
      "locked": false,
      "name": "Link",
      "persistentUuid": "6c60b580-5301-4d87-83dc-691b3a34c51b",
      "width": 0,
      "x": 53,
      "y": 68,
      "zOrder": 2,
      "numberProperties": [],
      "stringProperties": [],
      "initialVariables": [
        {
          "name": "to",
          "type": "string",
          "value": "prototype2"
        },
        {
          "name": "name",
          "type": "string",
          "value": "Platformer with build"
        }
      ]
    },
    {
      "angle": 0,
      "customSize": false,
      "height": 0,
      "layer": "",
      "locked": false,
      "name": "Link",
      "persistentUuid": "7eb24e10-daf6-4ff8-b731-88401f670486",
      "width": 0,
      "x": 53,
      "y": 104,
      "zOrder": 3,
      "numberProperties": [],
      "stringProperties": [],
      "initialVariables": [
        {
          "name": "to",
          "type": "string",
          "value": "protoype3"
        },
        {
          "name": "name",
          "type": "string",
          "value": "City builder but its a clicker"
        }
      ]
    }
  ],
  "objects": [
    {
      "bold": false,
      "italic": false,
      "name": "Link",
      "smoothed": true,
      "tags": "",
      "type": "TextObject::Text",
      "underlined": false,
      "variables": [
        {
          "name": "to",
          "type": "string",
          "value": ""
        },
        {
          "name": "name",
          "type": "string",
          "value": ""
        }
      ],
      "effects": [],
      "behaviors": [],
      "string": "<Link>",
      "font": "",
      "characterSize": 20,
      "color": {
        "b": 0,
        "g": 0,
        "r": 0
      }
    }
  ],
  "events": [
    {
      "disabled": false,
      "folded": false,
      "type": "BuiltinCommonInstructions::Standard",
      "conditions": [
        {
          "type": {
            "inverted": false,
            "value": "DepartScene"
          },
          "parameters": [
            ""
          ],
          "subInstructions": []
        }
      ],
      "actions": [
        {
          "type": {
            "inverted": false,
            "value": "TextObject::String"
          },
          "parameters": [
            "Link",
            "=",
            "Link.VariableString(name)"
          ],
          "subInstructions": []
        }
      ],
      "events": []
    },
    {
      "disabled": false,
      "folded": false,
      "type": "BuiltinCommonInstructions::Standard",
      "conditions": [
        {
          "type": {
            "inverted": false,
            "value": "MouseButtonReleased"
          },
          "parameters": [
            "",
            "Left"
          ],
          "subInstructions": []
        },
        {
          "type": {
            "inverted": false,
            "value": "SourisSurObjet"
          },
          "parameters": [
            "Link",
            "",
            "no",
            ""
          ],
          "subInstructions": []
        }
      ],
      "actions": [
        {
          "type": {
            "inverted": false,
            "value": "Scene"
          },
          "parameters": [
            "",
            "Link.VariableString(to)",
            "yes"
          ],
          "subInstructions": []
        }
      ],
      "events": []
    }
  ],
  "layers": [
    {
      "ambientLightColorB": 2,
      "ambientLightColorG": 134217728,
      "ambientLightColorR": 1597263169,
      "followBaseLayerCamera": false,
      "isLightingLayer": false,
      "name": "",
      "visibility": true,
      "cameras": [
        {
          "defaultSize": true,
          "defaultViewport": true,
          "height": 0,
          "viewportBottom": 1,
          "viewportLeft": 0,
          "viewportRight": 1,
          "viewportTop": 0,
          "width": 0
        }
      ],
      "effects": []
    }
  ],
  "behaviorsSharedData": [
    {
      "name": "PlatformerObject",
      "type": "PlatformBehavior::PlatformerObjectBehavior"
    }
  ]
}